python_x509_pkcs11/__init__.py
python_x509_pkcs11/ca.py
python_x509_pkcs11/crl.py
python_x509_pkcs11/crypto.py
python_x509_pkcs11/csr.py
python_x509_pkcs11/error.py
python_x509_pkcs11/lib.py
python_x509_pkcs11/ocsp.py
python_x509_pkcs11/pkcs11_handle.py
python_x509_pkcs11/privatekeys.py
python_x509_pkcs11/py.typed
python_x509_pkcs11-0.9.0.dist-info/LICENSE
python_x509_pkcs11-0.9.0.dist-info/WHEEL
python_x509_pkcs11-0.9.0.dist-info/METADATA
python_x509_pkcs11-0.9.0.dist-info/RECORD
