Metadata-Version: 2.1
Name: python_x509_pkcs11
Version: 0.9.0
Summary: Python async library for signing x509 using keys in a pkcs11 device such as an HSM.
Author-email: Victor Näslund <victor@sunet.se>, Magnus Svensson <masv@sunet.se>, Kushal Das <kushal@sunet.se>
Requires-Python: >=3.8
Requires-Dist: asn1crypto>=1.5.1
Requires-Dist: python-pkcs11>=0.7.0
Requires-Dist: aiohttp
Requires-Dist: cryptography >= 40.0
Project-URL: Source, https://github.com/SUNET/python_x509_pkcs11
